mein_paket/__init__.py
CentralIntelligenceAgency-0.1.dist-info/METADATA
CentralIntelligenceAgency-0.1.dist-info/WHEEL
CentralIntelligenceAgency-0.1.dist-info/entry_points.txt
CentralIntelligenceAgency-0.1.dist-info/top_level.txt
CentralIntelligenceAgency-0.1.dist-info/RECORD
