Metadata-Version: 2.1
Name: CentralIntelligenceAgency
Version: 0.1
Summary: Paket der Central Intelligence Agency
Home-page: https://github.com/dukeskardashian
Author: staatsberater
Author-email: staatsberater@instagram.com
